myemerge/__init__.py
myemerge/commons.py
myemerge/gettext.py
myemerge/locale/es/LC_MESSAGES/myemerge.mo
myemerge/locale/es.po
myemerge/locale/fr/LC_MESSAGES/myemerge.mo
myemerge/locale/fr.po
myemerge/locale/myemerge.pot
myemerge/myemerge_sync.py
myemerge/poethepoet.py
myemerge/reusing/cpupower.py
myemerge/reusing/github.py
myemerge-1.1.0.dist-info/METADATA
myemerge-1.1.0.dist-info/WHEEL
myemerge-1.1.0.dist-info/entry_points.txt
myemerge-1.1.0.dist-info/licenses/LICENSE.txt
myemerge-1.1.0.dist-info/RECORD
